bunny_teleop/__init__.py
bunny_teleop/bimanual_teleop_client.py
bunny_teleop/bimanual_teleop_server.py
bunny_teleop/init_config.py
bunny_teleop-0.0.2.dist-info/LICENSE
bunny_teleop-0.0.2.dist-info/METADATA
bunny_teleop-0.0.2.dist-info/WHEEL
bunny_teleop-0.0.2.dist-info/top_level.txt
bunny_teleop-0.0.2.dist-info/zip-safe
bunny_teleop-0.0.2.dist-info/RECORD
