Metadata-Version: 2.1
Name: bunny_teleop
Version: 0.0.2
Summary: Bimanual Dexterous Teleoperation with Real-Time Retargeting using VisionPro.
Home-page: 
Author: BunnyVisionPro
Author-email: 
Maintainer: BunnyVisionPro
Maintainer-email: 
License: MIT
Classifier: Development Status :: 3 - Alpha
Classifier: Intended Audience :: Developers
Classifier: Intended Audience :: Science/Research
Classifier: License :: OSI Approved :: MIT License
Classifier: Natural Language :: English
Classifier: Programming Language :: Python :: 3
Classifier: Programming Language :: Python :: 3.7
Classifier: Programming Language :: Python :: 3.8
Classifier: Programming Language :: Python :: 3.9
Classifier: Programming Language :: Python :: 3.10
Classifier: Programming Language :: Python :: 3.11
Classifier: Programming Language :: Python :: 3.12
Classifier: Topic :: Scientific/Engineering :: Artificial Intelligence
Requires-Python: >=3.7,<=3.12
License-File: LICENSE
Requires-Dist: pyzmq
Requires-Dist: numpy
Requires-Dist: tornado
Provides-Extra: dev
Requires-Dist: pytest ; extra == 'dev'
Requires-Dist: black ; extra == 'dev'
Requires-Dist: isort ; extra == 'dev'
Requires-Dist: mypy ; extra == 'dev'
Provides-Extra: example
